{
  "gitSyncId": "68f285cc5dc15a4fb128d19f_5e46185f-428d-416a-bac9-714329b7a556",
  "id": "Dashboard_mark_Attendance",
  "pluginId": "google-sheets-plugin",
  "pluginType": "SAAS",
  "unpublishedAction": {
    "actionConfiguration": {
      "encodeParamsToggle": true,
      "formData": {
        "command": {
          "data": "UPDATE_ONE"
        },
        "entityType": {
          "data": "ROWS"
        },
        "pagination": {
          "data": {
            "limit": "20",
            "offset": "0"
          }
        },
        "projection": {
          "data": []
        },
        "queryFormat": {
          "data": "ROWS"
        },
        "range": {
          "data": ""
        },
        "rowObjects": {
          "data": "{\n  \"rowIndex\": \"{{Table1.triggeredRowIndex + 1}}\",\n  \"Attendance_Status\": \"{{Table1.triggeredButtonColumn.label === 'Present' ? 'P' : 'A'}}\"\n}"
        },
        "sheetName": {
          "data": "Roster"
        },
        "sheetUrl": {
          "data": "https://docs.google.com/spreadsheets/d/1NzWyx91Jn4S2h85wK1y0ZRDVgxP5ri821ZhzcLhfXaw/edit"
        },
        "smartSubstitution": {
          "data": true
        },
        "tableHeaderIndex": {
          "data": "1"
        },
        "where": {
          "data": {
            "condition": "AND"
          }
        }
      },
      "paginationType": "NONE",
      "timeoutInMillisecond": 10000
    },
    "confirmBeforeExecute": false,
    "datasource": {
      "id": "Jds App Database",
      "isAutoGenerated": false,
      "name": "Jds App Database",
      "pluginId": "google-sheets-plugin"
    },
    "dynamicBindingPathList": [
      {
        "key": "formData.rowObjects.data"
      }
    ],
    "name": "mark_Attendance",
    "pageId": "Dashboard",
    "runBehaviour": "MANUAL",
    "userSetOnLoad": false
  }
}